brtgdb/__init__.py
brtgdb/brtgdb.py
brtgdb-0.3.6.dist-info/METADATA
brtgdb-0.3.6.dist-info/WHEEL
brtgdb-0.3.6.dist-info/top_level.txt
brtgdb-0.3.6.dist-info/RECORD
