Metadata-Version: 2.1
Name: brtgdb
Version: 0.3.6
Summary: A simple package for db connection.
Home-page: UNKNOWN
Author: Peter Raso
License: UNKNOWN
Platform: UNKNOWN
Requires-Python: >=3.7
Requires-Dist: SQLAlchemy (==1.4.21)
